toml_argparse/__init__.py
toml_argparse/argparse.py
toml_argparse-1.0.0.dist-info/LICENSE
toml_argparse-1.0.0.dist-info/METADATA
toml_argparse-1.0.0.dist-info/WHEEL
toml_argparse-1.0.0.dist-info/RECORD
