Metadata-Version: 2.1
Name: toml-argparse
Version: 1.0.0
Summary: This is a template repository for Python projects that use Poetry for their dependency management.
Home-page: https://github.com/florianmahner/toml-argparse
Author: florianmahner
Author-email: fflorian.mahner@gmail.com
Requires-Python: >=3.8,<4.0
Classifier: Programming Language :: Python :: 3
Classifier: Programming Language :: Python :: 3.8
Classifier: Programming Language :: Python :: 3.9
Classifier: Programming Language :: Python :: 3.10
Classifier: Programming Language :: Python :: 3.11
Requires-Dist: toml (>=0.10.2,<0.11.0)
Requires-Dist: types-toml (>=0.1.3,<0.2.0)
Project-URL: Documentation, https://florianmahner.github.io/toml-argparse/
Project-URL: Repository, https://github.com/florianmahner/toml-argparse
